openSAP32/__init__.py
openSAP32/_version.py
openSAP32/model/__init__.py
openSAP32/model/load.py
openSAP32/model/material.py
openSAP32/model/model.py
openSAP32/model/node.py
openSAP32/model/restrain.py
openSAP32/model/section.py
openSAP32/model/spring.py
openSAP32/model/structure.py
openSAP32/recorder/__init__.py
openSAP32/recorder/post.py
openSAP32/recorder/pre.py
openSAP32/recorder/recorder.py
openSAP32/solver/__init__.py
openSAP32/solver/mathematic.py
openSAP32/solver/truss.py
openSAP32-0.24.dist-info/LICENSE.txt
openSAP32-0.24.dist-info/METADATA
openSAP32-0.24.dist-info/WHEEL
openSAP32-0.24.dist-info/top_level.txt
openSAP32-0.24.dist-info/RECORD
