Metadata-Version: 2.1
Name: openSAP32
Version: 0.24
Summary: openSAP32 is open source software for modeling and perform structural analysis.
Home-page: https://github.com/dukenmarga/openSAP32
Author: Duken Marga
Author-email: dukenmarga@gmail.com
License: New BSD
Keywords: structural,analysis,civil,engineering,frame,fem,finite element
Platform: UNKNOWN
Classifier: Development Status :: 3 - Alpha
Classifier: Intended Audience :: Developers
Classifier: Intended Audience :: End Users/Desktop
Classifier: Topic :: Software Development :: Build Tools
Classifier: License :: OSI Approved :: BSD License
Classifier: Programming Language :: Python :: 3
Classifier: Programming Language :: Python :: 3.6
Classifier: Operating System :: OS Independent
Requires-Python: >=3.6
Requires-Dist: numpy (>=1.16)
